pasmopy/__init__.py
pasmopy/individualization.py
pasmopy/patient_model.py
pasmopy/validation.py
pasmopy/version.py
pasmopy/preprocessing/__init__.py
pasmopy/preprocessing/weighting_factors.py
pasmopy-0.5.0.dist-info/LICENSE
pasmopy-0.5.0.dist-info/METADATA
pasmopy-0.5.0.dist-info/WHEEL
pasmopy-0.5.0.dist-info/top_level.txt
pasmopy-0.5.0.dist-info/RECORD
